astro_trigger_filter-0.1.21.data/scripts/ambertf
astrotf/__init__.py
astrotf/radio.py
astrotf/radio_pulse.py
tests/__init__.py
tests/test_intersect.py
astro_trigger_filter-0.1.21.dist-info/LICENSE
astro_trigger_filter-0.1.21.dist-info/METADATA
astro_trigger_filter-0.1.21.dist-info/WHEEL
astro_trigger_filter-0.1.21.dist-info/entry_points.txt
astro_trigger_filter-0.1.21.dist-info/top_level.txt
astro_trigger_filter-0.1.21.dist-info/RECORD
